{"cameraMode":{"drawMode":0,"name":"Shaded","section":"Shading Mode"},"sceneLighting":true,"audioPlay":false,"sceneViewState":{"m_AlwaysRefresh":false,"showFog":true,"showSkybox":true,"showFlares":true,"showImageEffects":true,"showParticleSystems":true,"showVisualEffectGraphs":true,"m_FxEnabled":true},"in2DMode":false,"pivot":{"x":-0.2918597459793091,"y":-8.983507768789423e-7,"z":1.0211340188980103},"rotation":{"x":-0.09463270008563996,"y":0.7884588837623596,"z":-0.1254694163799286,"w":-0.594675600528717},"size":2.154960870742798,"orthographic":false}